CHANGES.txt
README.txt
TODO.txt
bootstrap.py
buildout.cfg
setup.py
test-plone-3.x.cfg
test-plone-4.x.cfg
versions.cfg
docs/LICENSE.GPL
docs/LICENSE.txt
pfg/__init__.py
pfg.donationform.egg-info/PKG-INFO
pfg.donationform.egg-info/SOURCES.txt
pfg.donationform.egg-info/dependency_links.txt
pfg.donationform.egg-info/entry_points.txt
pfg.donationform.egg-info/namespace_packages.txt
pfg.donationform.egg-info/not-zip-safe
pfg.donationform.egg-info/requires.txt
pfg.donationform.egg-info/top_level.txt
pfg/donationform/__init__.py
pfg/donationform/browser.py
pfg/donationform/cart.py
pfg/donationform/config.py
pfg/donationform/configure.zcml
pfg/donationform/donationfieldset.py
pfg/donationform/interfaces.py
pfg/donationform/setuphandlers.py
pfg/donationform/utils.py
pfg/donationform/profiles/default/factorytool.xml
pfg/donationform/profiles/default/is_pfgdonation_profile.txt
pfg/donationform/profiles/default/metadata.xml
pfg/donationform/profiles/default/rolemap.xml
pfg/donationform/profiles/default/skins.xml
pfg/donationform/profiles/default/types.xml
pfg/donationform/profiles/default/workflows.xml
pfg/donationform/profiles/default/types/DonationFieldSet.xml
pfg/donationform/profiles/default/types/Donation_Form.xml
pfg/donationform/profiles/default/types/FieldsetFolder.xml
pfg/donationform/profiles/default/types/FormFolder.xml
pfg/donationform/skins/pfg_donationform/donationfield_widget.pt
pfg/donationform/tests/__init__.py
pfg/donationform/tests/add-to-cart.txt
pfg/donationform/tests/base.py
pfg/donationform/tests/one-page-checkout.txt
pfg/donationform/tests/test_doctest.py