Metadata-Version: 1.0
Name: pfg.donationform
Version: 1.2.3
Summary: A PloneFormGen-based donation form that does checkout via PloneGetPaid.
Home-page: http://svn.plone.org/svn/collective/pfg.donationform
Author: David Glick, Groundwire
Author-email: davidglick@groundwire.org
License: GPL
Keywords: ploneformgen donation form getpaid
Platform: UNKNOWN
Classifier: Framework :: Plone
Classifier: License :: OSI Approved :: GNU General Public License (GPL)
